dire_jax/__init__.py
dire_jax/dire.py
dire_jax/dire_utils.py
dire_jax/hpindex.py
dire_jax/hpmetrics.py
dire_jax-0.2.1.dist-info/licenses/LICENSE
tests/__init__.py
tests/benchmark_memory.py
tests/check_memory_methods.py
tests/run_tests.py
tests/simple_test.py
tests/test_mpa_comparison.py
dire_jax-0.2.1.dist-info/METADATA
dire_jax-0.2.1.dist-info/WHEEL
dire_jax-0.2.1.dist-info/top_level.txt
dire_jax-0.2.1.dist-info/RECORD
