Metadata-Version: 2.4
Name: dire-jax
Version: 0.2.1
Summary: A JAX-based Dimension Reducer
Home-page: https://github.com/sashakolpakov/dire-jax
Author: Alexander Kolpakov (UATX), Igor Rivin (Temple University)
Author-email: Alexander Kolpakov <akolpakov@uaustin.org>, Igor Rivin <rivin@temple.edu>
License: Apache-2.0
Project-URL: Homepage, https://github.com/sashakolpakov/dire-jax
Project-URL: Documentation, https://sashakolpakov.github.io/dire-jax/
Project-URL: Repository, https://github.com/sashakolpakov/dire-jax
Project-URL: Bug Tracker, https://github.com/sashakolpakov/dire-jax/issues
Keywords: dimensionality reduction,jax,machine learning,visualization
Classifier: Programming Language :: Python :: 3
Classifier: License :: OSI Approved :: Apache Software License
Classifier: Operating System :: OS Independent
Requires-Python: >=3.8
License-File: LICENSE
Requires-Dist: jax
Requires-Dist: jaxlib
Requires-Dist: numpy
Requires-Dist: scipy
Requires-Dist: tqdm
Requires-Dist: pandas
Requires-Dist: plotly
Requires-Dist: loguru
Requires-Dist: scikit-learn
Provides-Extra: utils
Requires-Dist: ripser; extra == "utils"
Requires-Dist: persim; extra == "utils"
Requires-Dist: fastdtw; extra == "utils"
Requires-Dist: fast-twed; extra == "utils"
Requires-Dist: pot; extra == "utils"
Provides-Extra: all
Requires-Dist: ripser; extra == "all"
Requires-Dist: persim; extra == "all"
Requires-Dist: fastdtw; extra == "all"
Requires-Dist: fast-twed; extra == "all"
Requires-Dist: pot; extra == "all"
Dynamic: author
Dynamic: home-page
Dynamic: license-file
Dynamic: requires-python
